Lutil/__init__.py
Lutil/_exceptions.py
Lutil/_logging.py
Lutil/dataIO.py
Lutil/checkpoints/__init__.py
Lutil/checkpoints/_check_util.py
Lutil/checkpoints/_checkpoint.py
Lutil-0.1.10.dist-info/LICENSE
Lutil-0.1.10.dist-info/METADATA
Lutil-0.1.10.dist-info/WHEEL
Lutil-0.1.10.dist-info/top_level.txt
Lutil-0.1.10.dist-info/RECORD
