Metadata-Version: 2.1
Name: Lutil
Version: 0.1.10
Summary: Assist small-scale machine learning.
Home-page: https://github.com/Vopaaz/learning-utility
Author: Vopaaz
Author-email: liyifan945@163.com
License: UNKNOWN
Platform: UNKNOWN
Classifier: Programming Language :: Python :: 3.6
Classifier: Programming Language :: Python :: 3.7
Classifier: License :: OSI Approved :: GNU General Public License v3 (GPLv3)
Requires-Dist: pandas
Requires-Dist: chardet
Requires-Dist: numpy
Requires-Dist: joblib
